<?xml version="1.0" encoding="UTF-8" standalone="yes"?>
<features xmlns="http://karaf.apache.org/xmlns/features/v1.6.0" name="odl-ietf-model-rfc8525">
    <repository>mvn:org.opendaylight.ietf/odl-ietf-model-rfc6991/{{versionAsInProject}}/xml/features</repository>
    <repository>mvn:org.opendaylight.ietf/odl-ietf-model-rfc8342/{{versionAsInProject}}/xml/features</repository>
    <feature name="odl-ietf-model-rfc8525">
        <feature version="{{semVerRange}}">odl-ietf-model-rfc6991</feature>
        <feature version="{{semVerRange}}">odl-ietf-model-rfc8342</feature>
        <bundle>mvn:org.opendaylight.ietf.model/rfc8525/{{versionAsInProject}}</bundle>
    </feature>
</features>
